.coveragerc
CHANGES.txt
LICENSE.txt
MANIFEST.in
Makefile
README.rst
setup.cfg
setup.py
docs/Makefile
docs/conf.py
docs/designing.rst
docs/index.rst
docs/introduction.rst
docs/make.bat
docs/presentations.rst
docs/templates.rst
docs/usage.rst
docs/examples/hovercraft.css
docs/examples/hovercraft.rst
docs/examples/positions.rst
docs/examples/tutorial.css
docs/examples/tutorial.rst
docs/examples/images/hovercraft_logo.png
hovercraft/__init__.py
hovercraft/generate.py
hovercraft/parse.py
hovercraft/position.py
hovercraft/template.py
hovercraft.egg-info/PKG-INFO
hovercraft.egg-info/SOURCES.txt
hovercraft.egg-info/dependency_links.txt
hovercraft.egg-info/entry_points.txt
hovercraft.egg-info/not-zip-safe
hovercraft.egg-info/requires.txt
hovercraft.egg-info/top_level.txt
hovercraft/templates/reST.xsl
hovercraft/templates/default/template.cfg
hovercraft/templates/default/template.xsl
hovercraft/templates/default/css/highlight.css
hovercraft/templates/default/css/hovercraft.css
hovercraft/templates/default/css/impressConsole.css
hovercraft/templates/default/js/hovercraft.js
hovercraft/templates/default/js/impress.js
hovercraft/templates/default/js/impressConsole.js
hovercraft/templates/simple/template.cfg
hovercraft/templates/simple/template.xsl
hovercraft/templates/simple/css/highlight.css
hovercraft/templates/simple/css/hovercraft.css
hovercraft/templates/simple/js/hovercraft.js
hovercraft/templates/simple/js/impress.js