Metadata-Version: 1.1
Name: hovercraft
Version: 2.6
Summary: Makes impress.js presentations from reStructuredText
Home-page: https://github.com/regebro/hovercraft
Author: Lennart Regebro
Author-email: regebro@gmail.com
License: MIT
Keywords: presentations restructuredtext
Platform: UNKNOWN
Classifier: Development Status :: 5 - Production/Stable
Classifier: Topic :: Multimedia :: Graphics :: Presentation
Classifier: Topic :: Text Processing
Classifier: Operating System :: OS Independent
Classifier: Programming Language :: Python :: 3
Classifier: Programming Language :: Python :: 3 :: Only
Classifier: Programming Language :: Python :: 3.5
Classifier: Programming Language :: Python :: 3.6
Classifier: License :: OSI Approved :: MIT License
